unboil_pydantic_sqlalchemy/__init__.py
unboil_pydantic_sqlalchemy-0.1.2.dist-info/METADATA
unboil_pydantic_sqlalchemy-0.1.2.dist-info/WHEEL
unboil_pydantic_sqlalchemy-0.1.2.dist-info/licenses/LICENSE
unboil_pydantic_sqlalchemy-0.1.2.dist-info/RECORD
