Metadata-Version: 2.4
Name: unboil-pydantic-sqlalchemy
Version: 0.1.2
Summary: A library to seamlessly integrate SQLAlchemy models with Pydantic.
Project-URL: homepage, https://github.com/eyueldk/unboil-pydantic-sqlalchemy
Project-URL: repository, https://github.com/eyueldk/unboil-pydantic-sqlalchemy
Author: eyueldk
License: MIT
License-File: LICENSE
Keywords: pydantic,sqlalchemy,unboil
Classifier: Intended Audience :: Developers
Classifier: License :: OSI Approved :: MIT License
Classifier: Operating System :: OS Independent
Classifier: Programming Language :: Python :: 3
Classifier: Topic :: Software Development :: Libraries :: Python Modules
Requires-Python: >=3.9
Requires-Dist: sqlalchemy>=2.0.0
